{
 "_meta": {
  "total_questions": 3680,
  "years": [
   "100",
   "101",
   "102",
   "103",
   "104",
   "105",
   "106",
   "107",
   "108",
   "109",
   "110",
   "111",
   "112",
   "113",
   "114",
   "115"
  ],
  "generator": "scripts/analyze_corpus.py"
 },
 "by_type": {
  "申論題": {
   "total": 480,
   "師": 352,
   "士": 128,
   "by_year": {
    "100": 30,
    "101": 30,
    "102": 30,
    "103": 30,
    "104": 30,
    "105": 30,
    "106": 30,
    "107": 30,
    "108": 30,
    "109": 30,
    "110": 30,
    "111": 30,
    "112": 30,
    "113": 30,
    "114": 30,
    "115": 30
   }
  },
  "測驗題": {
   "total": 3200,
   "師": 640,
   "士": 2560,
   "by_year": {
    "100": 200,
    "101": 200,
    "102": 200,
    "103": 200,
    "104": 200,
    "105": 200,
    "106": 200,
    "107": 200,
    "108": 200,
    "109": 200,
    "110": 200,
    "111": 200,
    "112": 200,
    "113": 200,
    "114": 200,
    "115": 200
   }
  }
 },
 "by_system": {
  "水系統": {
   "total": 615,
   "師": 165,
   "士": 450,
   "by_year": {
    "100": 26,
    "101": 38,
    "102": 40,
    "103": 32,
    "104": 34,
    "105": 47,
    "106": 32,
    "107": 37,
    "108": 34,
    "109": 44,
    "110": 52,
    "111": 36,
    "112": 45,
    "113": 38,
    "114": 43,
    "115": 37
   }
  },
  "化學系統": {
   "total": 541,
   "師": 128,
   "士": 413,
   "by_year": {
    "100": 36,
    "101": 42,
    "102": 39,
    "103": 36,
    "104": 29,
    "105": 32,
    "106": 35,
    "107": 38,
    "108": 34,
    "109": 32,
    "110": 28,
    "111": 34,
    "112": 29,
    "113": 32,
    "114": 30,
    "115": 35
   }
  },
  "警報系統": {
   "total": 585,
   "師": 132,
   "士": 453,
   "by_year": {
    "100": 40,
    "101": 33,
    "102": 33,
    "103": 37,
    "104": 34,
    "105": 37,
    "106": 36,
    "107": 32,
    "108": 34,
    "109": 35,
    "110": 37,
    "111": 41,
    "112": 42,
    "113": 32,
    "114": 44,
    "115": 38
   }
  },
  "避難系統": {
   "total": 480,
   "師": 126,
   "士": 354,
   "by_year": {
    "100": 27,
    "101": 29,
    "102": 29,
    "103": 27,
    "104": 26,
    "105": 27,
    "106": 24,
    "107": 26,
    "108": 32,
    "109": 35,
    "110": 30,
    "111": 26,
    "112": 41,
    "113": 40,
    "114": 30,
    "115": 31
   }
  }
 },
 "by_equipment": {
  "消防幫浦/加壓送水裝置": {
   "total": 151,
   "師": 42,
   "士": 109,
   "by_year": {
    "100": 8,
    "101": 10,
    "102": 8,
    "103": 11,
    "104": 7,
    "105": 13,
    "106": 8,
    "107": 13,
    "108": 8,
    "109": 9,
    "110": 12,
    "111": 11,
    "112": 12,
    "113": 8,
    "114": 6,
    "115": 7
   }
  },
  "泡沫滅火設備": {
   "total": 140,
   "師": 28,
   "士": 112,
   "by_year": {
    "100": 5,
    "101": 11,
    "102": 11,
    "103": 13,
    "104": 5,
    "105": 12,
    "106": 8,
    "107": 10,
    "108": 8,
    "109": 13,
    "110": 10,
    "111": 6,
    "112": 10,
    "113": 8,
    "114": 5,
    "115": 5
   }
  },
  "室內消防栓": {
   "total": 117,
   "師": 29,
   "士": 88,
   "by_year": {
    "100": 4,
    "101": 6,
    "102": 6,
    "103": 6,
    "104": 6,
    "105": 8,
    "106": 4,
    "107": 10,
    "108": 10,
    "109": 12,
    "110": 8,
    "111": 4,
    "112": 8,
    "113": 7,
    "114": 7,
    "115": 11
   }
  },
  "火警自動警報設備": {
   "total": 437,
   "師": 82,
   "士": 355,
   "by_year": {
    "100": 32,
    "101": 24,
    "102": 23,
    "103": 27,
    "104": 21,
    "105": 26,
    "106": 30,
    "107": 27,
    "108": 26,
    "109": 22,
    "110": 28,
    "111": 29,
    "112": 32,
    "113": 24,
    "114": 35,
    "115": 31
   }
  },
  "滅火器": {
   "total": 142,
   "師": 51,
   "士": 91,
   "by_year": {
    "100": 9,
    "101": 12,
    "102": 10,
    "103": 6,
    "104": 9,
    "105": 4,
    "106": 8,
    "107": 13,
    "108": 9,
    "109": 10,
    "110": 10,
    "111": 10,
    "112": 7,
    "113": 7,
    "114": 7,
    "115": 11
   }
  },
  "消防專用蓄水池": {
   "total": 26,
   "師": 7,
   "士": 19,
   "by_year": {
    "100": 2,
    "101": 1,
    "102": 1,
    "104": 1,
    "105": 1,
    "106": 1,
    "107": 1,
    "109": 3,
    "110": 2,
    "111": 2,
    "112": 4,
    "113": 2,
    "114": 3,
    "115": 2
   }
  },
  "瓦斯漏氣火警自動警報設備": {
   "total": 96,
   "師": 18,
   "士": 78,
   "by_year": {
    "100": 6,
    "101": 5,
    "102": 4,
    "103": 5,
    "104": 6,
    "105": 6,
    "106": 8,
    "107": 6,
    "108": 5,
    "109": 6,
    "110": 5,
    "111": 5,
    "112": 11,
    "113": 6,
    "114": 6,
    "115": 6
   }
  },
  "水霧滅火設備": {
   "total": 90,
   "師": 20,
   "士": 70,
   "by_year": {
    "100": 3,
    "101": 10,
    "102": 13,
    "103": 4,
    "104": 3,
    "105": 8,
    "106": 4,
    "107": 4,
    "108": 7,
    "109": 5,
    "110": 5,
    "111": 4,
    "112": 5,
    "113": 4,
    "114": 7,
    "115": 4
   }
  },
  "自動撒水設備": {
   "total": 258,
   "師": 67,
   "士": 191,
   "by_year": {
    "100": 9,
    "101": 15,
    "102": 15,
    "103": 16,
    "104": 18,
    "105": 18,
    "106": 14,
    "107": 13,
    "108": 15,
    "109": 14,
    "110": 24,
    "111": 19,
    "112": 22,
    "113": 16,
    "114": 16,
    "115": 14
   }
  },
  "防災監控系統綜合操作裝置": {
   "total": 42,
   "師": 13,
   "士": 29,
   "by_year": {
    "100": 2,
    "101": 1,
    "102": 3,
    "103": 1,
    "105": 1,
    "107": 2,
    "108": 2,
    "109": 3,
    "110": 1,
    "111": 5,
    "112": 5,
    "113": 8,
    "114": 6,
    "115": 2
   }
  },
  "排煙設備": {
   "total": 125,
   "師": 39,
   "士": 86,
   "by_year": {
    "100": 7,
    "101": 7,
    "102": 5,
    "103": 10,
    "104": 5,
    "105": 9,
    "106": 6,
    "107": 2,
    "108": 14,
    "109": 7,
    "110": 6,
    "111": 9,
    "112": 11,
    "113": 9,
    "114": 11,
    "115": 7
   }
  },
  "緊急照明設備": {
   "total": 70,
   "師": 21,
   "士": 49,
   "by_year": {
    "100": 3,
    "101": 8,
    "102": 4,
    "103": 4,
    "104": 3,
    "105": 2,
    "106": 4,
    "107": 7,
    "108": 3,
    "109": 4,
    "110": 3,
    "111": 3,
    "112": 4,
    "113": 6,
    "114": 5,
    "115": 7
   }
  },
  "連結送水管": {
   "total": 49,
   "師": 13,
   "士": 36,
   "by_year": {
    "100": 3,
    "101": 2,
    "102": 1,
    "103": 3,
    "104": 3,
    "105": 3,
    "106": 3,
    "107": 3,
    "108": 2,
    "109": 3,
    "110": 7,
    "112": 2,
    "113": 5,
    "114": 7,
    "115": 2
   }
  },
  "二氧化碳滅火設備": {
   "total": 163,
   "師": 30,
   "士": 133,
   "by_year": {
    "100": 12,
    "101": 13,
    "102": 14,
    "103": 10,
    "104": 8,
    "105": 9,
    "106": 11,
    "107": 10,
    "108": 12,
    "109": 8,
    "110": 10,
    "111": 13,
    "112": 8,
    "113": 9,
    "114": 10,
    "115": 6
   }
  },
  "標示設備": {
   "total": 103,
   "師": 31,
   "士": 72,
   "by_year": {
    "100": 8,
    "101": 7,
    "102": 7,
    "103": 4,
    "104": 9,
    "105": 4,
    "106": 7,
    "107": 5,
    "108": 6,
    "109": 7,
    "110": 8,
    "111": 2,
    "112": 3,
    "113": 14,
    "114": 5,
    "115": 7
   }
  },
  "緊急廣播設備": {
   "total": 84,
   "師": 18,
   "士": 66,
   "by_year": {
    "100": 6,
    "101": 6,
    "102": 3,
    "103": 7,
    "104": 8,
    "105": 6,
    "106": 5,
    "107": 2,
    "108": 2,
    "109": 5,
    "110": 6,
    "111": 6,
    "112": 10,
    "113": 3,
    "114": 5,
    "115": 4
   }
  },
  "無線電通信輔助設備": {
   "total": 27,
   "師": 5,
   "士": 22,
   "by_year": {
    "100": 2,
    "101": 1,
    "102": 1,
    "103": 1,
    "105": 3,
    "107": 3,
    "108": 2,
    "109": 3,
    "111": 2,
    "112": 5,
    "114": 3,
    "115": 1
   }
  },
  "避難器具": {
   "total": 141,
   "師": 36,
   "士": 105,
   "by_year": {
    "100": 5,
    "101": 9,
    "102": 8,
    "103": 8,
    "104": 11,
    "105": 11,
    "106": 10,
    "107": 9,
    "108": 8,
    "109": 9,
    "110": 10,
    "111": 9,
    "112": 11,
    "113": 9,
    "114": 8,
    "115": 6
   }
  },
  "手動報警設備": {
   "total": 28,
   "師": 6,
   "士": 22,
   "by_year": {
    "100": 2,
    "101": 1,
    "102": 1,
    "103": 3,
    "104": 2,
    "105": 1,
    "106": 2,
    "107": 1,
    "108": 2,
    "109": 3,
    "110": 2,
    "111": 1,
    "112": 2,
    "113": 2,
    "114": 2,
    "115": 1
   }
  },
  "緊急電源插座": {
   "total": 31,
   "師": 4,
   "士": 27,
   "by_year": {
    "100": 2,
    "101": 1,
    "102": 2,
    "103": 2,
    "104": 2,
    "105": 1,
    "107": 3,
    "108": 1,
    "109": 3,
    "110": 2,
    "112": 4,
    "113": 2,
    "114": 3,
    "115": 3
   }
  },
  "乾粉滅火設備": {
   "total": 134,
   "師": 29,
   "士": 105,
   "by_year": {
    "100": 9,
    "101": 12,
    "102": 15,
    "103": 10,
    "104": 5,
    "105": 6,
    "106": 11,
    "107": 10,
    "108": 12,
    "109": 7,
    "110": 7,
    "111": 6,
    "112": 4,
    "113": 7,
    "114": 7,
    "115": 6
   }
  },
  "鹵化烴滅火設備": {
   "total": 56,
   "師": 15,
   "士": 41,
   "by_year": {
    "100": 5,
    "101": 4,
    "102": 2,
    "103": 4,
    "104": 4,
    "105": 2,
    "106": 2,
    "107": 2,
    "108": 5,
    "110": 2,
    "111": 1,
    "112": 2,
    "113": 7,
    "114": 9,
    "115": 5
   }
  },
  "二氧化碳及惰性氣體滅火設備": {
   "total": 33,
   "師": 6,
   "士": 27,
   "by_year": {
    "100": 2,
    "102": 2,
    "103": 1,
    "104": 1,
    "105": 1,
    "106": 2,
    "107": 2,
    "108": 1,
    "111": 2,
    "112": 3,
    "113": 2,
    "114": 9,
    "115": 5
   }
  },
  "室外消防栓": {
   "total": 68,
   "師": 12,
   "士": 56,
   "by_year": {
    "100": 1,
    "101": 4,
    "102": 6,
    "103": 2,
    "104": 6,
    "105": 4,
    "106": 4,
    "107": 5,
    "108": 6,
    "109": 3,
    "110": 4,
    "111": 4,
    "112": 4,
    "113": 4,
    "114": 5,
    "115": 6
   }
  },
  "住宅用火災警報器": {
   "total": 33,
   "師": 21,
   "士": 12,
   "by_year": {
    "100": 2,
    "101": 1,
    "102": 4,
    "103": 1,
    "104": 3,
    "105": 4,
    "106": 1,
    "108": 2,
    "109": 3,
    "110": 2,
    "111": 1,
    "112": 2,
    "113": 5,
    "114": 1,
    "115": 1
   }
  },
  "射水設備": {
   "total": 14,
   "師": 5,
   "士": 9,
   "by_year": {
    "101": 1,
    "102": 2,
    "104": 1,
    "107": 2,
    "108": 1,
    "109": 1,
    "111": 1,
    "112": 1,
    "113": 2,
    "115": 2
   }
  },
  "簡易自動滅火設備": {
   "total": 21,
   "師": 5,
   "士": 16,
   "by_year": {
    "101": 3,
    "103": 2,
    "104": 4,
    "105": 2,
    "106": 2,
    "108": 1,
    "109": 1,
    "111": 3,
    "112": 2,
    "113": 1
   }
  },
  "冷卻撒水設備": {
   "total": 14,
   "師": 1,
   "士": 13,
   "by_year": {
    "102": 1,
    "104": 1,
    "107": 1,
    "108": 2,
    "110": 3,
    "112": 3,
    "113": 1,
    "115": 2
   }
  },
  "119火災通報設備": {
   "total": 29,
   "師": 8,
   "士": 21,
   "by_year": {
    "108": 3,
    "109": 4,
    "110": 2,
    "111": 6,
    "112": 7,
    "113": 1,
    "114": 4,
    "115": 2
   }
  },
  "水道連結型自動撒水設備": {
   "total": 20,
   "師": 11,
   "士": 9,
   "by_year": {
    "108": 2,
    "109": 2,
    "110": 5,
    "111": 2,
    "112": 3,
    "113": 2,
    "114": 2,
    "115": 2
   }
  }
 },
 "by_law": {
  "消防法": {
   "total": 213,
   "師": 96,
   "士": 117,
   "by_year": {
    "100": 14,
    "101": 14,
    "102": 12,
    "103": 16,
    "104": 24,
    "105": 9,
    "106": 14,
    "107": 11,
    "108": 15,
    "109": 10,
    "110": 11,
    "111": 13,
    "112": 11,
    "113": 12,
    "114": 13,
    "115": 14
   }
  },
  "消防法施行細則": {
   "total": 63,
   "師": 26,
   "士": 37,
   "by_year": {
    "100": 3,
    "101": 4,
    "102": 8,
    "103": 8,
    "104": 5,
    "105": 1,
    "106": 2,
    "107": 5,
    "108": 4,
    "109": 5,
    "110": 3,
    "111": 6,
    "112": 5,
    "113": 1,
    "114": 2,
    "115": 1
   }
  },
  "公共危險物品及可燃性高壓氣體製造儲存處理場所設置標準暨安全管理辦法": {
   "total": 316,
   "師": 119,
   "士": 197,
   "by_year": {
    "100": 23,
    "101": 21,
    "102": 20,
    "103": 16,
    "104": 19,
    "105": 13,
    "106": 25,
    "107": 24,
    "108": 15,
    "109": 14,
    "110": 25,
    "111": 26,
    "112": 20,
    "113": 17,
    "114": 18,
    "115": 20
   }
  },
  "防火牆及防火水幕設置基準": {
   "total": 41,
   "師": 17,
   "士": 24,
   "by_year": {
    "100": 5,
    "101": 2,
    "102": 2,
    "103": 5,
    "104": 2,
    "105": 4,
    "106": 4,
    "107": 3,
    "108": 2,
    "109": 3,
    "110": 1,
    "111": 1,
    "112": 3,
    "113": 2,
    "114": 2
   }
  },
  "防焰性能認證實施辦法": {
   "total": 47,
   "師": 39,
   "士": 8,
   "by_year": {
    "100": 7,
    "101": 6,
    "102": 2,
    "103": 2,
    "104": 6,
    "105": 3,
    "106": 4,
    "107": 3,
    "108": 4,
    "109": 1,
    "110": 2,
    "111": 3,
    "112": 1,
    "113": 2,
    "115": 1
   }
  },
  "消防幫浦加壓送水裝置等及配管摩擦損失計算基準": {
   "total": 40,
   "師": 23,
   "士": 17,
   "by_year": {
    "100": 3,
    "102": 3,
    "104": 4,
    "105": 3,
    "106": 1,
    "107": 4,
    "108": 3,
    "109": 4,
    "110": 1,
    "111": 4,
    "112": 4,
    "113": 1,
    "114": 4,
    "115": 1
   }
  },
  "消防安全設備及必要檢修項目檢修基準": {
   "total": 184,
   "師": 57,
   "士": 127,
   "by_year": {
    "100": 12,
    "101": 6,
    "102": 11,
    "103": 5,
    "104": 6,
    "105": 8,
    "106": 7,
    "107": 10,
    "108": 12,
    "109": 12,
    "110": 19,
    "111": 12,
    "112": 27,
    "113": 14,
    "114": 12,
    "115": 11
   }
  },
  "建築技術規則建築設計施工編": {
   "total": 116,
   "師": 51,
   "士": 65,
   "by_year": {
    "100": 7,
    "101": 11,
    "102": 5,
    "103": 11,
    "104": 8,
    "105": 6,
    "106": 11,
    "107": 6,
    "108": 6,
    "109": 9,
    "110": 8,
    "111": 6,
    "112": 6,
    "113": 4,
    "114": 7,
    "115": 5
   }
  },
  "各類場所消防安全設備設置標準": {
   "total": 842,
   "師": 404,
   "士": 438,
   "by_year": {
    "100": 36,
    "101": 44,
    "102": 68,
    "103": 51,
    "104": 46,
    "105": 49,
    "106": 50,
    "107": 68,
    "108": 60,
    "109": 51,
    "110": 44,
    "111": 50,
    "112": 63,
    "113": 59,
    "114": 66,
    "115": 37
   }
  },
  "原有合法建築物公共安全改善辦法": {
   "total": 8,
   "師": 5,
   "士": 3,
   "by_year": {
    "100": 1,
    "101": 2,
    "104": 1,
    "105": 1,
    "108": 1,
    "110": 1,
    "112": 1
   }
  },
  "消防設備人員法": {
   "total": 66,
   "師": 30,
   "士": 36,
   "by_year": {
    "100": 4,
    "101": 2,
    "102": 4,
    "103": 6,
    "104": 10,
    "105": 4,
    "106": 5,
    "107": 2,
    "108": 2,
    "109": 5,
    "110": 4,
    "111": 3,
    "112": 3,
    "113": 5,
    "114": 5,
    "115": 2
   }
  },
  "消防設備人員法施行細則": {
   "total": 4,
   "師": 0,
   "士": 4,
   "by_year": {
    "100": 1,
    "108": 1,
    "110": 1,
    "112": 1
   }
  },
  "消防設備人員專業訓練機關構學校團體認可及管理辦法": {
   "total": 16,
   "師": 11,
   "士": 5,
   "by_year": {
    "100": 2,
    "102": 2,
    "103": 2,
    "105": 1,
    "108": 4,
    "109": 2,
    "111": 2,
    "112": 1
   }
  },
  "消防安全設備檢修專業機構管理辦法": {
   "total": 51,
   "師": 17,
   "士": 34,
   "by_year": {
    "100": 1,
    "101": 3,
    "102": 2,
    "103": 2,
    "104": 6,
    "105": 2,
    "106": 3,
    "107": 1,
    "108": 5,
    "109": 5,
    "110": 2,
    "111": 4,
    "112": 3,
    "113": 5,
    "114": 3,
    "115": 4
   }
  },
  "消防安全設備檢修及申報辦法": {
   "total": 51,
   "師": 21,
   "士": 30,
   "by_year": {
    "100": 1,
    "101": 5,
    "102": 1,
    "103": 1,
    "104": 3,
    "105": 1,
    "106": 3,
    "107": 10,
    "108": 3,
    "109": 5,
    "110": 3,
    "111": 3,
    "112": 4,
    "113": 2,
    "114": 4,
    "115": 2
   }
  },
  "滅火器認可基準": {
   "total": 12,
   "師": 6,
   "士": 6,
   "by_year": {
    "100": 1,
    "101": 1,
    "103": 1,
    "106": 1,
    "107": 3,
    "109": 3,
    "112": 1,
    "114": 1
   }
  },
  "住宅用火災警報器設置辦法": {
   "total": 6,
   "師": 5,
   "士": 1,
   "by_year": {
    "100": 1,
    "101": 1,
    "108": 1,
    "109": 1,
    "110": 2
   }
  },
  "出口標示燈及避難方向指示燈認可基準": {
   "total": 9,
   "師": 4,
   "士": 5,
   "by_year": {
    "101": 1,
    "103": 1,
    "104": 2,
    "105": 1,
    "106": 1,
    "108": 1,
    "113": 1,
    "114": 1
   }
  },
  "複合用途建築物判斷基準": {
   "total": 4,
   "師": 3,
   "士": 1,
   "by_year": {
    "101": 1,
    "108": 1,
    "109": 1,
    "110": 1
   }
  },
  "建築法": {
   "total": 5,
   "師": 3,
   "士": 2,
   "by_year": {
    "101": 1,
    "102": 1,
    "105": 1,
    "109": 1,
    "110": 1
   }
  },
  "消防幫浦認可基準": {
   "total": 2,
   "師": 0,
   "士": 2,
   "by_year": {
    "101": 1,
    "113": 1
   }
  },
  "撒水頭認可基準": {
   "total": 6,
   "師": 2,
   "士": 4,
   "by_year": {
    "101": 1,
    "103": 1,
    "107": 1,
    "110": 2,
    "111": 1
   }
  },
  "泡沫噴頭認可基準": {
   "total": 1,
   "師": 0,
   "士": 1,
   "by_year": {
    "101": 1
   }
  },
  "消防機關辦理建築物消防安全設備審查及查驗作業基準": {
   "total": 13,
   "師": 7,
   "士": 6,
   "by_year": {
    "101": 1,
    "102": 1,
    "104": 1,
    "105": 1,
    "106": 2,
    "107": 1,
    "108": 1,
    "109": 1,
    "111": 1,
    "112": 2,
    "114": 1
   }
  },
  "二氧化碳滅火設備各種標示規格": {
   "total": 5,
   "師": 1,
   "士": 4,
   "by_year": {
    "102": 1,
    "103": 1,
    "104": 1,
    "110": 1,
    "111": 1
   }
  },
  "可燃性高壓氣體儲存場所防爆牆設置基準": {
   "total": 18,
   "師": 7,
   "士": 11,
   "by_year": {
    "100": 1,
    "102": 3,
    "103": 2,
    "105": 1,
    "106": 1,
    "108": 2,
    "109": 1,
    "110": 1,
    "111": 2,
    "112": 4
   }
  },
  "消防安全設備測試報告書測試方法及判定要領": {
   "total": 50,
   "師": 15,
   "士": 35,
   "by_year": {
    "100": 1,
    "101": 1,
    "104": 1,
    "105": 4,
    "106": 1,
    "108": 3,
    "109": 7,
    "110": 2,
    "111": 2,
    "112": 10,
    "113": 11,
    "114": 4,
    "115": 3
   }
  },
  "金屬製避難梯認可基準": {
   "total": 2,
   "師": 1,
   "士": 1,
   "by_year": {
    "100": 1,
    "104": 1
   }
  },
  "滅火器用滅火藥劑認可基準": {
   "total": 3,
   "師": 1,
   "士": 2,
   "by_year": {
    "104": 1,
    "106": 1,
    "107": 1
   }
  },
  "火警探測器認可基準": {
   "total": 14,
   "師": 10,
   "士": 4,
   "by_year": {
    "100": 1,
    "101": 1,
    "103": 1,
    "104": 1,
    "105": 1,
    "108": 3,
    "111": 2,
    "112": 2,
    "113": 1,
    "115": 1
   }
  },
  "住宅用火災警報器認可基準": {
   "total": 5,
   "師": 3,
   "士": 2,
   "by_year": {
    "104": 1,
    "105": 1,
    "108": 1,
    "109": 1,
    "113": 1
   }
  },
  "可燃性高壓氣體儲存場所防護牆設置基準": {
   "total": 6,
   "師": 4,
   "士": 2,
   "by_year": {
    "103": 1,
    "106": 2,
    "107": 1,
    "108": 1,
    "109": 1
   }
  },
  "緩降機認可基準": {
   "total": 4,
   "師": 3,
   "士": 1,
   "by_year": {
    "102": 1,
    "106": 1,
    "107": 1,
    "112": 1
   }
  },
  "避難器具支固器具及固定部之結構強度計算及施工方法": {
   "total": 8,
   "師": 4,
   "士": 4,
   "by_year": {
    "106": 1,
    "107": 1,
    "108": 1,
    "109": 1,
    "110": 1,
    "111": 1,
    "112": 2
   }
  },
  "消防安全設備設計監造測試及檢修作業辦法": {
   "total": 3,
   "師": 2,
   "士": 1,
   "by_year": {
    "101": 1,
    "107": 1,
    "108": 1
   }
  },
  "消防設備人員執業執照登記辦法": {
   "total": 9,
   "師": 5,
   "士": 4,
   "by_year": {
    "109": 1,
    "110": 3,
    "111": 1,
    "112": 1,
    "113": 2,
    "114": 1
   }
  },
  "服勤人員訓練與專業機構登錄及管理辦法": {
   "total": 1,
   "師": 0,
   "士": 1,
   "by_year": {
    "111": 1
   }
  },
  "乾粉滅火設備各種標示規格": {
   "total": 2,
   "師": 1,
   "士": 1,
   "by_year": {
    "102": 1,
    "111": 1
   }
  },
  "119火災通報裝置認可基準": {
   "total": 2,
   "師": 1,
   "士": 1,
   "by_year": {
    "109": 1,
    "111": 1
   }
  },
  "緊急廣播設備用揚聲器認可基準": {
   "total": 6,
   "師": 3,
   "士": 3,
   "by_year": {
    "101": 1,
    "105": 1,
    "110": 1,
    "111": 1,
    "112": 1,
    "113": 1
   }
  },
  "防火管理人訓練與專業機構登錄及管理辦法": {
   "total": 2,
   "師": 1,
   "士": 1,
   "by_year": {
    "110": 1,
    "113": 1
   }
  },
  "消防水帶用快速接頭認可基準": {
   "total": 1,
   "師": 0,
   "士": 1,
   "by_year": {
    "113": 1
   }
  },
  "流水檢知裝置認可基準": {
   "total": 1,
   "師": 0,
   "士": 1,
   "by_year": {
    "113": 1
   }
  },
  "緊急電源容量計算基準": {
   "total": 5,
   "師": 5,
   "士": 0,
   "by_year": {
    "101": 1,
    "103": 1,
    "106": 1,
    "110": 1,
    "114": 1
   }
  },
  "火警受信總機認可基準": {
   "total": 7,
   "師": 7,
   "士": 0,
   "by_year": {
    "101": 1,
    "104": 1,
    "105": 1,
    "108": 1,
    "109": 2,
    "110": 1
   }
  },
  "滅火器性能檢查及藥劑更換充填作業專業廠商認可及管理要點": {
   "total": 3,
   "師": 3,
   "士": 0,
   "by_year": {
    "102": 1,
    "109": 2
   }
  },
  "公共危險物品試驗方法及判定基準": {
   "total": 1,
   "師": 1,
   "士": 0,
   "by_year": {
    "105": 1
   }
  },
  "潔淨區消防安全設備設置要點": {
   "total": 8,
   "師": 8,
   "士": 0,
   "by_year": {
    "106": 2,
    "109": 2,
    "110": 2,
    "112": 1,
    "115": 1
   }
  },
  "一齊開放閥認可基準": {
   "total": 1,
   "師": 1,
   "士": 0,
   "by_year": {
    "107": 1
   }
  },
  "119火災通報裝置設置及維護注意事項": {
   "total": 1,
   "師": 1,
   "士": 0,
   "by_year": {
    "108": 1
   }
  },
  "水道連結型自動撒水設備設置基準": {
   "total": 7,
   "師": 7,
   "士": 0,
   "by_year": {
    "108": 1,
    "109": 1,
    "110": 3,
    "114": 1,
    "115": 1
   }
  },
  "消防機具器材及設備認可實施辦法": {
   "total": 2,
   "師": 2,
   "士": 0,
   "by_year": {
    "109": 1,
    "110": 1
   }
  }
 },
 "by_article": {
  "消防法第12條": {
   "total": 3,
   "師": 0,
   "士": 3,
   "by_year": {
    "100": 1,
    "105": 1,
    "112": 1
   }
  },
  "施行細則第4條": {
   "total": 1,
   "師": 0,
   "士": 1,
   "by_year": {
    "100": 1
   }
  },
  "防火牆及防火水幕設置基準第7條": {
   "total": 1,
   "師": 0,
   "士": 1,
   "by_year": {
    "100": 1
   }
  },
  "消防法第21條": {
   "total": 1,
   "師": 0,
   "士": 1,
   "by_year": {
    "100": 1
   }
  },
  "消防法第11條": {
   "total": 21,
   "師": 15,
   "士": 6,
   "by_year": {
    "100": 3,
    "101": 3,
    "102": 1,
    "103": 2,
    "104": 2,
    "106": 1,
    "107": 1,
    "108": 1,
    "109": 2,
    "110": 2,
    "111": 2,
    "113": 1
   }
  },
  "設置標準第162條": {
   "total": 1,
   "師": 0,
   "士": 1,
   "by_year": {
    "100": 1
   }
  },
  "設置標準第160條": {
   "total": 8,
   "師": 7,
   "士": 1,
   "by_year": {
    "100": 1,
    "101": 1,
    "103": 1,
    "105": 1,
    "107": 1,
    "109": 1,
    "111": 1,
    "112": 1
   }
  },
  "設置標準第238條": {
   "total": 1,
   "師": 0,
   "士": 1,
   "by_year": {
    "100": 1
   }
  },
  "設置標準第127條": {
   "total": 1,
   "師": 0,
   "士": 1,
   "by_year": {
    "100": 1
   }
  },
  "建築技術規則建築設計施工編第97條": {
   "total": 1,
   "師": 0,
   "士": 1,
   "by_year": {
    "100": 1
   }
  },
  "消防法第6條": {
   "total": 11,
   "師": 5,
   "士": 6,
   "by_year": {
    "101": 1,
    "102": 1,
    "103": 1,
    "104": 2,
    "105": 2,
    "106": 1,
    "108": 1,
    "112": 2
   }
  },
  "施行細則第15條": {
   "total": 7,
   "師": 3,
   "士": 4,
   "by_year": {
    "101": 1,
    "102": 1,
    "104": 1,
    "106": 1,
    "109": 3
   }
  },
  "設置標準第12條": {
   "total": 19,
   "師": 8,
   "士": 11,
   "by_year": {
    "100": 1,
    "101": 2,
    "103": 1,
    "107": 2,
    "108": 4,
    "109": 4,
    "110": 1,
    "111": 2,
    "112": 1,
    "113": 1
   }
  },
  "設置標準第5條": {
   "total": 1,
   "師": 0,
   "士": 1,
   "by_year": {
    "101": 1
   }
  },
  "消防法第10條": {
   "total": 1,
   "師": 0,
   "士": 1,
   "by_year": {
    "101": 1
   }
  },
  "建築法第34條之1": {
   "total": 2,
   "師": 0,
   "士": 2,
   "by_year": {
    "101": 1,
    "115": 1
   }
  },
  "設置標準第16條": {
   "total": 2,
   "師": 1,
   "士": 1,
   "by_year": {
    "101": 1,
    "108": 1
   }
  },
  "消防法第15條": {
   "total": 1,
   "師": 0,
   "士": 1,
   "by_year": {
    "102": 1
   }
  },
  "消防法第26條": {
   "total": 3,
   "師": 1,
   "士": 2,
   "by_year": {
    "102": 1,
    "106": 1,
    "109": 1
   }
  },
  "設置標準第197條": {
   "total": 1,
   "師": 0,
   "士": 1,
   "by_year": {
    "102": 1
   }
  },
  "消防法第13條": {
   "total": 16,
   "師": 10,
   "士": 6,
   "by_year": {
    "100": 2,
    "102": 2,
    "104": 1,
    "105": 1,
    "108": 1,
    "109": 2,
    "110": 2,
    "111": 1,
    "112": 1,
    "113": 2,
    "115": 1
   }
  },
  "設置標準第155條": {
   "total": 2,
   "師": 1,
   "士": 1,
   "by_year": {
    "100": 1,
    "102": 1
   }
  },
  "設置標準第188條": {
   "total": 15,
   "師": 13,
   "士": 2,
   "by_year": {
    "100": 1,
    "101": 1,
    "102": 2,
    "103": 1,
    "104": 1,
    "105": 2,
    "106": 1,
    "108": 3,
    "109": 1,
    "110": 1,
    "112": 1
   }
  },
  "設置標準第179條": {
   "total": 2,
   "師": 1,
   "士": 1,
   "by_year": {
    "102": 1,
    "107": 1
   }
  },
  "設置標準第190條": {
   "total": 4,
   "師": 3,
   "士": 1,
   "by_year": {
    "102": 1,
    "103": 1,
    "108": 1,
    "111": 1
   }
  },
  "建築技術規則建築設計施工編第227條": {
   "total": 1,
   "師": 0,
   "士": 1,
   "by_year": {
    "103": 1
   }
  },
  "施行細則第13條": {
   "total": 7,
   "師": 1,
   "士": 6,
   "by_year": {
    "101": 1,
    "103": 1,
    "104": 1,
    "108": 1,
    "109": 1,
    "110": 1,
    "111": 1
   }
  },
  "施行細則第17條": {
   "total": 1,
   "師": 0,
   "士": 1,
   "by_year": {
    "103": 1
   }
  },
  "設置標準第37條": {
   "total": 1,
   "師": 0,
   "士": 1,
   "by_year": {
    "103": 1
   }
  },
  "設置標準第120條": {
   "total": 6,
   "師": 5,
   "士": 1,
   "by_year": {
    "103": 1,
    "106": 1,
    "107": 2,
    "108": 1,
    "109": 1
   }
  },
  "消防法第9條": {
   "total": 9,
   "師": 5,
   "士": 4,
   "by_year": {
    "102": 1,
    "103": 1,
    "104": 2,
    "108": 1,
    "110": 2,
    "112": 1,
    "114": 1
   }
  },
  "施行細則第6條": {
   "total": 1,
   "師": 0,
   "士": 1,
   "by_year": {
    "104": 1
   }
  },
  "消防安全設備檢修專業機構管理辦法第4條": {
   "total": 1,
   "師": 0,
   "士": 1,
   "by_year": {
    "104": 1
   }
  },
  "消防法第15條之1": {
   "total": 2,
   "師": 1,
   "士": 1,
   "by_year": {
    "104": 2
   }
  },
  "設置標準第8條": {
   "total": 2,
   "師": 0,
   "士": 2,
   "by_year": {
    "104": 1,
    "108": 1
   }
  },
  "設置標準第18條": {
   "total": 4,
   "師": 3,
   "士": 1,
   "by_year": {
    "101": 1,
    "103": 1,
    "104": 1,
    "109": 1
   }
  },
  "設置標準第52條": {
   "total": 1,
   "師": 0,
   "士": 1,
   "by_year": {
    "105": 1
   }
  },
  "施行細則第14條": {
   "total": 1,
   "師": 0,
   "士": 1,
   "by_year": {
    "106": 1
   }
  },
  "消防法第7條": {
   "total": 6,
   "師": 1,
   "士": 5,
   "by_year": {
    "101": 1,
    "106": 1,
    "108": 1,
    "109": 1,
    "114": 2
   }
  },
  "設置標準第23條": {
   "total": 1,
   "師": 0,
   "士": 1,
   "by_year": {
    "107": 1
   }
  },
  "消防法第38條": {
   "total": 4,
   "師": 0,
   "士": 4,
   "by_year": {
    "108": 3,
    "112": 1
   }
  },
  "公危辦法第20條": {
   "total": 1,
   "師": 0,
   "士": 1,
   "by_year": {
    "108": 1
   }
  },
  "消防法第42條": {
   "total": 2,
   "師": 1,
   "士": 1,
   "by_year": {
    "100": 1,
    "108": 1
   }
  },
  "公危辦法第74條": {
   "total": 1,
   "師": 0,
   "士": 1,
   "by_year": {
    "108": 1
   }
  },
  "設置標準第112條": {
   "total": 2,
   "師": 1,
   "士": 1,
   "by_year": {
    "102": 1,
    "108": 1
   }
  },
  "設置標準第28條": {
   "total": 4,
   "師": 3,
   "士": 1,
   "by_year": {
    "101": 1,
    "108": 1,
    "111": 1,
    "113": 1
   }
  },
  "施行細則第7條": {
   "total": 1,
   "師": 0,
   "士": 1,
   "by_year": {
    "109": 1
   }
  },
  "消防法第21條之1": {
   "total": 1,
   "師": 0,
   "士": 1,
   "by_year": {
    "110": 1
   }
  },
  "消防法第14條之1": {
   "total": 1,
   "師": 0,
   "士": 1,
   "by_year": {
    "110": 1
   }
  },
  "消防法第41條之1": {
   "total": 1,
   "師": 0,
   "士": 1,
   "by_year": {
    "110": 1
   }
  },
  "消防法第1條": {
   "total": 1,
   "師": 0,
   "士": 1,
   "by_year": {
    "110": 1
   }
  },
  "消防法第3條": {
   "total": 1,
   "師": 0,
   "士": 1,
   "by_year": {
    "110": 1
   }
  },
  "消防法第37條": {
   "total": 2,
   "師": 1,
   "士": 1,
   "by_year": {
    "100": 1,
    "110": 1
   }
  },
  "公危辦法第38條": {
   "total": 4,
   "師": 2,
   "士": 2,
   "by_year": {
    "103": 1,
    "107": 1,
    "110": 1,
    "111": 1
   }
  },
  "建築技術規則建築設計施工編第76條": {
   "total": 1,
   "師": 0,
   "士": 1,
   "by_year": {
    "111": 1
   }
  },
  "設置標準第111條之1": {
   "total": 1,
   "師": 0,
   "士": 1,
   "by_year": {
    "112": 1
   }
  },
  "設置標準第214條": {
   "total": 1,
   "師": 0,
   "士": 1,
   "by_year": {
    "113": 1
   }
  },
  "消防法第15條之5": {
   "total": 3,
   "師": 2,
   "士": 1,
   "by_year": {
    "113": 2,
    "114": 1
   }
  },
  "設置標準第21條": {
   "total": 3,
   "師": 2,
   "士": 1,
   "by_year": {
    "104": 1,
    "107": 1,
    "114": 1
   }
  },
  "設置標準第167條": {
   "total": 1,
   "師": 0,
   "士": 1,
   "by_year": {
    "114": 1
   }
  },
  "消防法第15條之2": {
   "total": 1,
   "師": 0,
   "士": 1,
   "by_year": {
    "115": 1
   }
  },
  "公危辦法第13條": {
   "total": 1,
   "師": 1,
   "士": 0,
   "by_year": {
    "100": 1
   }
  },
  "消防法第2條": {
   "total": 2,
   "師": 2,
   "士": 0,
   "by_year": {
    "100": 1,
    "111": 1
   }
  },
  "消防法第28條": {
   "total": 1,
   "師": 1,
   "士": 0,
   "by_year": {
    "100": 1
   }
  },
  "消防法第30條": {
   "total": 1,
   "師": 1,
   "士": 0,
   "by_year": {
    "100": 1
   }
  },
  "消防法第32條": {
   "total": 1,
   "師": 1,
   "士": 0,
   "by_year": {
    "100": 1
   }
  },
  "消防法第42條之1": {
   "total": 1,
   "師": 1,
   "士": 0,
   "by_year": {
    "100": 1
   }
  },
  "設置標準第116條": {
   "total": 3,
   "師": 3,
   "士": 0,
   "by_year": {
    "100": 1,
    "102": 1,
    "103": 1
   }
  },
  "設置標準第117條": {
   "total": 3,
   "師": 3,
   "士": 0,
   "by_year": {
    "100": 1,
    "102": 1,
    "103": 1
   }
  },
  "設置標準第156條": {
   "total": 1,
   "師": 1,
   "士": 0,
   "by_year": {
    "100": 1
   }
  },
  "設置標準第157條": {
   "total": 8,
   "師": 8,
   "士": 0,
   "by_year": {
    "100": 1,
    "101": 1,
    "102": 1,
    "104": 1,
    "107": 1,
    "110": 1,
    "111": 1,
    "112": 1
   }
  },
  "設置標準第189條": {
   "total": 4,
   "師": 4,
   "士": 0,
   "by_year": {
    "100": 1,
    "102": 1,
    "104": 1,
    "112": 1
   }
  },
  "設置標準第165條": {
   "total": 1,
   "師": 1,
   "士": 0,
   "by_year": {
    "100": 1
   }
  },
  "設置標準第47條": {
   "total": 2,
   "師": 2,
   "士": 0,
   "by_year": {
    "100": 1,
    "112": 1
   }
  },
  "設置標準第14條": {
   "total": 11,
   "師": 11,
   "士": 0,
   "by_year": {
    "100": 1,
    "101": 1,
    "102": 1,
    "103": 1,
    "104": 1,
    "105": 1,
    "106": 1,
    "108": 1,
    "111": 1,
    "113": 1,
    "114": 1
   }
  },
  "設置標準第84條": {
   "total": 8,
   "師": 8,
   "士": 0,
   "by_year": {
    "100": 1,
    "101": 1,
    "102": 1,
    "105": 1,
    "110": 1,
    "113": 1,
    "114": 1,
    "115": 1
   }
  },
  "設置標準第99條": {
   "total": 7,
   "師": 7,
   "士": 0,
   "by_year": {
    "100": 1,
    "101": 1,
    "102": 1,
    "104": 1,
    "113": 1,
    "114": 1,
    "115": 1
   }
  },
  "設置標準第24條": {
   "total": 1,
   "師": 1,
   "士": 0,
   "by_year": {
    "101": 1
   }
  },
  "設置標準第79條": {
   "total": 2,
   "師": 2,
   "士": 0,
   "by_year": {
    "101": 1,
    "111": 1
   }
  },
  "設置標準第19條": {
   "total": 4,
   "師": 4,
   "士": 0,
   "by_year": {
    "101": 1,
    "105": 1,
    "106": 1,
    "113": 1
   }
  },
  "設置標準第133條": {
   "total": 10,
   "師": 10,
   "士": 0,
   "by_year": {
    "101": 1,
    "102": 1,
    "103": 1,
    "104": 1,
    "105": 1,
    "106": 1,
    "107": 1,
    "109": 1,
    "110": 1,
    "111": 1
   }
  },
  "設置標準第141條": {
   "total": 4,
   "師": 4,
   "士": 0,
   "by_year": {
    "101": 1,
    "102": 1,
    "104": 1,
    "107": 1
   }
  },
  "設置標準第146條之3": {
   "total": 4,
   "師": 4,
   "士": 0,
   "by_year": {
    "101": 1,
    "104": 1,
    "109": 1,
    "110": 1
   }
  },
  "設置標準第61條": {
   "total": 2,
   "師": 2,
   "士": 0,
   "by_year": {
    "101": 1,
    "107": 1
   }
  },
  "設置標準第85條": {
   "total": 4,
   "師": 4,
   "士": 0,
   "by_year": {
    "101": 1,
    "108": 1,
    "111": 1,
    "113": 1
   }
  },
  "公危辦法第70條": {
   "total": 1,
   "師": 1,
   "士": 0,
   "by_year": {
    "102": 1
   }
  },
  "施行細則第27條": {
   "total": 1,
   "師": 1,
   "士": 0,
   "by_year": {
    "102": 1
   }
  },
  "施行細則第19條之1": {
   "total": 1,
   "師": 1,
   "士": 0,
   "by_year": {
    "102": 1
   }
  },
  "施行細則第33條": {
   "total": 1,
   "師": 1,
   "士": 0,
   "by_year": {
    "102": 1
   }
  },
  "設置標準第175條": {
   "total": 1,
   "師": 1,
   "士": 0,
   "by_year": {
    "102": 1
   }
  },
  "設置標準第146條之2": {
   "total": 6,
   "師": 6,
   "士": 0,
   "by_year": {
    "102": 1,
    "104": 1,
    "109": 2,
    "110": 1,
    "111": 1
   }
  },
  "設置標準第146條之7": {
   "total": 6,
   "師": 6,
   "士": 0,
   "by_year": {
    "102": 1,
    "103": 1,
    "105": 1,
    "107": 1,
    "108": 1,
    "111": 1
   }
  },
  "設置標準第82條": {
   "total": 4,
   "師": 4,
   "士": 0,
   "by_year": {
    "102": 1,
    "105": 1,
    "106": 1,
    "109": 1
   }
  },
  "設置標準第102條": {
   "total": 3,
   "師": 3,
   "士": 0,
   "by_year": {
    "102": 1,
    "104": 1,
    "112": 1
   }
  },
  "設置標準第124條": {
   "total": 1,
   "師": 1,
   "士": 0,
   "by_year": {
    "103": 1
   }
  },
  "設置標準第129條": {
   "total": 1,
   "師": 1,
   "士": 0,
   "by_year": {
    "103": 1
   }
  },
  "設置標準第161條": {
   "total": 2,
   "師": 2,
   "士": 0,
   "by_year": {
    "103": 1,
    "112": 1
   }
  },
  "設置標準第83條": {
   "total": 3,
   "師": 3,
   "士": 0,
   "by_year": {
    "103": 1,
    "108": 1,
    "115": 1
   }
  },
  "設置標準第125條": {
   "total": 2,
   "師": 2,
   "士": 0,
   "by_year": {
    "104": 1,
    "110": 1
   }
  },
  "設置標準第159條": {
   "total": 5,
   "師": 5,
   "士": 0,
   "by_year": {
    "104": 1,
    "108": 1,
    "109": 1,
    "110": 1,
    "113": 1
   }
  },
  "建築技術規則第97條": {
   "total": 1,
   "師": 1,
   "士": 0,
   "by_year": {
    "104": 1
   }
  },
  "設置標準第115條": {
   "total": 2,
   "師": 2,
   "士": 0,
   "by_year": {
    "105": 1,
    "107": 1
   }
  },
  "設置標準第113條": {
   "total": 1,
   "師": 1,
   "士": 0,
   "by_year": {
    "105": 1
   }
  },
  "設置標準第163條": {
   "total": 1,
   "師": 1,
   "士": 0,
   "by_year": {
    "105": 1
   }
  },
  "設置標準第178條": {
   "total": 2,
   "師": 2,
   "士": 0,
   "by_year": {
    "105": 1,
    "112": 1
   }
  },
  "公危辦法第73條": {
   "total": 1,
   "師": 1,
   "士": 0,
   "by_year": {
    "106": 1
   }
  },
  "建築技術規則建築設計施工編第99條之1": {
   "total": 1,
   "師": 1,
   "士": 0,
   "by_year": {
    "106": 1
   }
  },
  "建築法第77條之2": {
   "total": 1,
   "師": 1,
   "士": 0,
   "by_year": {
    "106": 1
   }
  },
  "建築法第95條之1": {
   "total": 1,
   "師": 1,
   "士": 0,
   "by_year": {
    "106": 1
   }
  },
  "設置標準第38條": {
   "total": 1,
   "師": 1,
   "士": 0,
   "by_year": {
    "106": 1
   }
  },
  "設置標準第164條": {
   "total": 2,
   "師": 2,
   "士": 0,
   "by_year": {
    "106": 1,
    "111": 1
   }
  },
  "設置標準第97條": {
   "total": 4,
   "師": 4,
   "士": 0,
   "by_year": {
    "106": 1,
    "107": 1,
    "108": 1,
    "109": 1
   }
  },
  "設置標準第3條": {
   "total": 2,
   "師": 2,
   "士": 0,
   "by_year": {
    "107": 1,
    "110": 1
   }
  },
  "設置標準第94條": {
   "total": 6,
   "師": 6,
   "士": 0,
   "by_year": {
    "107": 1,
    "110": 1,
    "113": 1,
    "114": 2,
    "115": 1
   }
  },
  "檢修專業機構管理辦法第8條": {
   "total": 1,
   "師": 1,
   "士": 0,
   "by_year": {
    "108": 1
   }
  },
  "檢修專業機構管理辦法第17條": {
   "total": 1,
   "師": 1,
   "士": 0,
   "by_year": {
    "108": 1
   }
  },
  "檢修專業機構管理辦法第18條": {
   "total": 1,
   "師": 1,
   "士": 0,
   "by_year": {
    "108": 1
   }
  },
  "建築技術規則建築設計施工編第88條": {
   "total": 1,
   "師": 1,
   "士": 0,
   "by_year": {
    "109": 1
   }
  },
  "建築法第9條": {
   "total": 1,
   "師": 1,
   "士": 0,
   "by_year": {
    "109": 1
   }
  },
  "建築技術規則建築設計施工編第1條": {
   "total": 1,
   "師": 1,
   "士": 0,
   "by_year": {
    "109": 1
   }
  },
  "建築技術規則建築設計施工編第259條": {
   "total": 2,
   "師": 2,
   "士": 0,
   "by_year": {
    "109": 1,
    "110": 1
   }
  },
  "設置標準第57條": {
   "total": 2,
   "師": 2,
   "士": 0,
   "by_year": {
    "109": 1,
    "114": 1
   }
  },
  "設置標準第69條": {
   "total": 1,
   "師": 1,
   "士": 0,
   "by_year": {
    "109": 1
   }
  },
  "複合用途建築物判斷基準第2條": {
   "total": 1,
   "師": 1,
   "士": 0,
   "by_year": {
    "110": 1
   }
  },
  "設置標準第40條": {
   "total": 2,
   "師": 2,
   "士": 0,
   "by_year": {
    "110": 1,
    "113": 1
   }
  },
  "設置標準第210條": {
   "total": 2,
   "師": 2,
   "士": 0,
   "by_year": {
    "110": 1,
    "114": 1
   }
  },
  "設置標準第193條": {
   "total": 1,
   "師": 1,
   "士": 0,
   "by_year": {
    "110": 1
   }
  },
  "設置標準第53條": {
   "total": 1,
   "師": 1,
   "士": 0,
   "by_year": {
    "110": 1
   }
  },
  "設置標準第73條": {
   "total": 1,
   "師": 1,
   "士": 0,
   "by_year": {
    "110": 1
   }
  },
  "設置標準第32條": {
   "total": 3,
   "師": 3,
   "士": 0,
   "by_year": {
    "110": 1,
    "111": 1,
    "113": 1
   }
  },
  "建築技術規則建築設計施工編第108條": {
   "total": 1,
   "師": 1,
   "士": 0,
   "by_year": {
    "110": 1
   }
  },
  "建築技術規則建築設計施工編第205條": {
   "total": 1,
   "師": 1,
   "士": 0,
   "by_year": {
    "110": 1
   }
  },
  "設置標準第184條": {
   "total": 1,
   "師": 1,
   "士": 0,
   "by_year": {
    "110": 1
   }
  },
  "設置標準第88條": {
   "total": 2,
   "師": 2,
   "士": 0,
   "by_year": {
    "110": 1,
    "112": 1
   }
  },
  "公危辦法第73條之1": {
   "total": 1,
   "師": 1,
   "士": 0,
   "by_year": {
    "111": 1
   }
  },
  "公危辦法第73條之2": {
   "total": 2,
   "師": 2,
   "士": 0,
   "by_year": {
    "111": 1,
    "112": 1
   }
  },
  "設置標準第30條之1": {
   "total": 1,
   "師": 1,
   "士": 0,
   "by_year": {
    "111": 1
   }
  },
  "設置標準第78條": {
   "total": 1,
   "師": 1,
   "士": 0,
   "by_year": {
    "111": 1
   }
  },
  "設置標準第87條": {
   "total": 1,
   "師": 1,
   "士": 0,
   "by_year": {
    "111": 1
   }
  },
  "施行細則第21條": {
   "total": 1,
   "師": 1,
   "士": 0,
   "by_year": {
    "112": 1
   }
  },
  "公危辦法第42條": {
   "total": 1,
   "師": 1,
   "士": 0,
   "by_year": {
    "112": 1
   }
  },
  "設置標準第46條": {
   "total": 1,
   "師": 1,
   "士": 0,
   "by_year": {
    "112": 1
   }
  },
  "設置標準第123條": {
   "total": 1,
   "師": 1,
   "士": 0,
   "by_year": {
    "112": 1
   }
  },
  "建築技術規則建築設計施工編第93條": {
   "total": 1,
   "師": 1,
   "士": 0,
   "by_year": {
    "113": 1
   }
  },
  "設置標準第31條": {
   "total": 1,
   "師": 1,
   "士": 0,
   "by_year": {
    "114": 1
   }
  },
  "測試報告書第9條": {
   "total": 1,
   "師": 1,
   "士": 0,
   "by_year": {
    "115": 1
   }
  }
 },
 "by_topic": {
  "煙控與煙流": {
   "total": 66,
   "師": 15,
   "士": 51,
   "by_year": {
    "100": 3,
    "101": 5,
    "102": 3,
    "103": 5,
    "104": 4,
    "105": 5,
    "106": 5,
    "107": 2,
    "108": 6,
    "109": 5,
    "110": 4,
    "111": 3,
    "112": 4,
    "113": 4,
    "114": 5,
    "115": 3
   }
  },
  "燃燒理論": {
   "total": 132,
   "師": 5,
   "士": 127,
   "by_year": {
    "100": 9,
    "101": 10,
    "102": 8,
    "103": 5,
    "104": 7,
    "105": 7,
    "106": 11,
    "107": 11,
    "108": 3,
    "109": 1,
    "110": 11,
    "111": 12,
    "112": 11,
    "113": 9,
    "114": 7,
    "115": 10
   }
  },
  "閃燃": {
   "total": 7,
   "師": 3,
   "士": 4,
   "by_year": {
    "100": 1,
    "102": 1,
    "107": 1,
    "108": 3,
    "109": 1
   }
  },
  "熱傳": {
   "total": 80,
   "師": 5,
   "士": 75,
   "by_year": {
    "100": 6,
    "101": 3,
    "102": 5,
    "103": 5,
    "104": 6,
    "105": 4,
    "106": 3,
    "107": 5,
    "108": 3,
    "109": 2,
    "110": 6,
    "111": 7,
    "112": 7,
    "113": 6,
    "114": 5,
    "115": 7
   }
  },
  "區劃空間火災發展": {
   "total": 14,
   "師": 6,
   "士": 8,
   "by_year": {
    "100": 6,
    "107": 1,
    "108": 3,
    "109": 1,
    "112": 2,
    "114": 1
   }
  },
  "火災化學與化學計量": {
   "total": 45,
   "師": 6,
   "士": 39,
   "by_year": {
    "100": 2,
    "101": 1,
    "102": 4,
    "103": 1,
    "104": 2,
    "105": 3,
    "106": 2,
    "108": 4,
    "109": 4,
    "110": 6,
    "111": 1,
    "112": 6,
    "113": 4,
    "114": 4,
    "115": 1
   }
  },
  "危險物品分類與特性": {
   "total": 40,
   "師": 8,
   "士": 32,
   "by_year": {
    "100": 5,
    "101": 1,
    "103": 5,
    "105": 3,
    "107": 1,
    "108": 4,
    "109": 4,
    "110": 3,
    "111": 1,
    "112": 3,
    "113": 4,
    "114": 3,
    "115": 3
   }
  },
  "靜電": {
   "total": 31,
   "師": 3,
   "士": 28,
   "by_year": {
    "100": 3,
    "101": 2,
    "102": 2,
    "104": 2,
    "105": 2,
    "106": 2,
    "107": 2,
    "108": 1,
    "109": 3,
    "110": 1,
    "111": 4,
    "112": 1,
    "113": 2,
    "114": 1,
    "115": 3
   }
  },
  "燃燒界限與爆炸界限": {
   "total": 10,
   "師": 2,
   "士": 8,
   "by_year": {
    "100": 1,
    "105": 1,
    "108": 5,
    "109": 2,
    "113": 1
   }
  },
  "爆炸": {
   "total": 102,
   "師": 9,
   "士": 93,
   "by_year": {
    "100": 7,
    "101": 4,
    "102": 5,
    "103": 6,
    "104": 5,
    "105": 6,
    "106": 7,
    "107": 3,
    "108": 6,
    "109": 6,
    "110": 8,
    "111": 4,
    "112": 10,
    "113": 6,
    "114": 8,
    "115": 11
   }
  },
  "建築物火災性狀": {
   "total": 13,
   "師": 7,
   "士": 6,
   "by_year": {
    "100": 2,
    "101": 1,
    "107": 3,
    "108": 2,
    "109": 3,
    "110": 1,
    "111": 1
   }
  },
  "特殊場所火災": {
   "total": 26,
   "師": 8,
   "士": 18,
   "by_year": {
    "100": 4,
    "101": 1,
    "102": 1,
    "103": 3,
    "104": 2,
    "105": 1,
    "106": 1,
    "107": 5,
    "109": 2,
    "110": 3,
    "112": 1,
    "113": 1,
    "114": 1
   }
  },
  "電氣火災": {
   "total": 48,
   "師": 5,
   "士": 43,
   "by_year": {
    "100": 2,
    "101": 4,
    "102": 4,
    "103": 4,
    "104": 3,
    "105": 3,
    "106": 2,
    "107": 3,
    "108": 2,
    "109": 6,
    "110": 3,
    "111": 3,
    "112": 1,
    "113": 2,
    "114": 3,
    "115": 3
   }
  },
  "滅火原理與滅火藥劑": {
   "total": 60,
   "師": 4,
   "士": 56,
   "by_year": {
    "100": 4,
    "101": 3,
    "102": 7,
    "103": 5,
    "104": 7,
    "105": 4,
    "107": 5,
    "108": 4,
    "109": 9,
    "110": 4,
    "111": 3,
    "112": 1,
    "113": 3,
    "114": 1
   }
  },
  "火災調查與鑑識": {
   "total": 13,
   "師": 2,
   "士": 11,
   "by_year": {
    "100": 1,
    "103": 2,
    "104": 1,
    "105": 1,
    "106": 2,
    "107": 1,
    "110": 3,
    "111": 2
   }
  },
  "火羽流與頂棚噴流": {
   "total": 9,
   "師": 3,
   "士": 6,
   "by_year": {
    "100": 2,
    "105": 1,
    "108": 2,
    "109": 3,
    "110": 1
   }
  },
  "預混與擴散燃燒": {
   "total": 3,
   "師": 1,
   "士": 2,
   "by_year": {
    "101": 1,
    "109": 1,
    "111": 1
   }
  },
  "爆燃": {
   "total": 2,
   "師": 1,
   "士": 1,
   "by_year": {
    "102": 1,
    "108": 1
   }
  },
  "人員避難行為": {
   "total": 2,
   "師": 2,
   "士": 0,
   "by_year": {
    "101": 1,
    "105": 1
   }
  }
 },
 "by_flag": {
  "找錯誤": {
   "total": 896,
   "師": 206,
   "士": 690,
   "by_year": {
    "100": 66,
    "101": 51,
    "102": 55,
    "103": 63,
    "104": 69,
    "105": 67,
    "106": 47,
    "107": 40,
    "108": 54,
    "109": 34,
    "110": 38,
    "111": 51,
    "112": 68,
    "113": 76,
    "114": 82,
    "115": 35
   }
  },
  "計算題": {
   "total": 553,
   "師": 193,
   "士": 360,
   "by_year": {
    "100": 35,
    "101": 27,
    "102": 35,
    "103": 28,
    "104": 29,
    "105": 24,
    "106": 35,
    "107": 36,
    "108": 48,
    "109": 48,
    "110": 43,
    "111": 21,
    "112": 43,
    "113": 31,
    "114": 40,
    "115": 30
   }
  },
  "找正確": {
   "total": 567,
   "師": 156,
   "士": 411,
   "by_year": {
    "100": 20,
    "101": 25,
    "102": 27,
    "103": 27,
    "104": 50,
    "105": 23,
    "106": 24,
    "107": 36,
    "108": 41,
    "109": 32,
    "110": 43,
    "111": 40,
    "112": 51,
    "113": 29,
    "114": 33,
    "115": 66
   }
  },
  "圖形題": {
   "total": 11,
   "師": 7,
   "士": 4,
   "by_year": {
    "100": 3,
    "102": 1,
    "103": 1,
    "104": 1,
    "111": 1,
    "113": 1,
    "114": 1,
    "115": 2
   }
  },
  "更正答案": {
   "total": 14,
   "師": 2,
   "士": 12,
   "by_year": {
    "104": 2,
    "105": 2,
    "106": 4,
    "108": 1,
    "109": 1,
    "110": 1,
    "112": 1,
    "113": 1,
    "114": 1
   }
  }
 }
}